tdd_mcp/__init__.py
tdd_mcp/main.py
tdd_mcp/domain/__init__.py
tdd_mcp/domain/events.py
tdd_mcp/domain/exceptions.py
tdd_mcp/domain/session.py
tdd_mcp/handlers/__init__.py
tdd_mcp/handlers/guidance_handlers.py
tdd_mcp/handlers/logging_handlers.py
tdd_mcp/handlers/session_handlers.py
tdd_mcp/handlers/workflow_handlers.py
tdd_mcp/repository/__init__.py
tdd_mcp/repository/base.py
tdd_mcp/repository/filesystem.py
tdd_mcp/repository/memory.py
tdd_mcp/utils/__init__.py
tdd_mcp/utils/config.py
tdd_mcp/utils/logging.py
tdd_mcp-0.0.1.dist-info/METADATA
tdd_mcp-0.0.1.dist-info/WHEEL
tdd_mcp-0.0.1.dist-info/entry_points.txt
tdd_mcp-0.0.1.dist-info/licenses/LICENSE
tdd_mcp-0.0.1.dist-info/RECORD
