Metadata-Version: 2.4
Name: tdd-mcp
Version: 0.0.1
Summary: A Model Context Protocol (MCP) server that enforces disciplined Test-Driven Development workflows
Project-URL: Homepage, https://github.com/tinmancoding/tdd-mcp
Project-URL: Repository, https://github.com/tinmancoding/tdd-mcp
Project-URL: Issues, https://github.com/tinmancoding/tdd-mcp/issues
Author-email: Tin Man <135335469+tinmancoding@users.noreply.github.com>
License: MIT
License-File: LICENSE
Keywords: development-workflow,event-sourcing,mcp,tdd,test-driven-development,testing
Classifier: Development Status :: 3 - Alpha
Classifier: Intended Audience :: Developers
Classifier: License :: OSI Approved :: MIT License
Classifier: Programming Language :: Python :: 3
Classifier: Programming Language :: Python :: 3.12
Classifier: Topic :: Software Development :: Libraries :: Python Modules
Classifier: Topic :: Software Development :: Testing
Requires-Python: >=3.12
Requires-Dist: fastmcp
Requires-Dist: pydantic>=2.0.0
